Metadata-Version: 1.1
Name: simple-venn
Version: 0.1.0
Summary: Simple venn diagrams
Home-page: https://github.com/msto/simple-venn
Author: Matthew Stone
Author-email: matthew(dot)stone12(at)gmail.com
License: MIT
Keywords: venn diagram matplotlib
Platform: UNKNOWN
Classifier: Development Status :: 3 - Alpha
Classifier: Intended Audience :: Science/Research
Classifier: License :: OSI Approved :: MIT License
Classifier: Programming Language :: Python :: 3
Classifier: Topic :: Scientific/Engineering :: Visualization
